ssm_cache/__init__.py
ssm_cache/cache.py
ssm_cache/filters.py
ssm_cache-2.10.dist-info/LICENSE
ssm_cache-2.10.dist-info/METADATA
ssm_cache-2.10.dist-info/WHEEL
ssm_cache-2.10.dist-info/top_level.txt
ssm_cache-2.10.dist-info/RECORD
