Metadata-Version: 2.1
Name: ssm-cache
Version: 2.10
Summary: AWS System Manager Parameter Store caching client for Python
Home-page: https://github.com/alexcasalboni/ssm-cache-python
Author: Alex Casalboni
Author-email: alex@alexcasalboni.com
License: MIT
Download-URL: https://github.com/alexcasalboni/ssm-cache-python/archive/2.10.tar.gz
Keywords: aws,amazon-web-services,aws-lambda,aws-ssm,parameter-store
Platform: UNKNOWN
Requires-Dist: boto3
Requires-Dist: future
